wordpress2puput/__init__.py
wordpress2puput/management/__init__.py
wordpress2puput/management/commands/__init__.py
wordpress2puput/management/commands/wp2puput.py
wordpress_to_puput-0.4.dist-info/LICENSE
wordpress_to_puput-0.4.dist-info/METADATA
wordpress_to_puput-0.4.dist-info/WHEEL
wordpress_to_puput-0.4.dist-info/top_level.txt
wordpress_to_puput-0.4.dist-info/RECORD
