Metadata-Version: 2.1
Name: wordpress-to-puput
Version: 0.4
Summary: Import your Wordpress blog data into Puput.
Home-page: http://github.com/APSL/wordpress-to-puput
Author: David Valera
Author-email: david.valera.martinez@gmail.com
License: UNKNOWN
Keywords: django wagtail puput blog cms wordpress
Platform: UNKNOWN
Classifier: Environment :: Web Environment
Classifier: Framework :: Django
Classifier: Intended Audience :: Developers
Classifier: Programming Language :: Python
Classifier: Programming Language :: Python :: 2
Classifier: Programming Language :: Python :: 2.7
Classifier: Programming Language :: Python :: 3
Classifier: Programming Language :: Python :: 3.3
Classifier: Programming Language :: Python :: 3.4
Classifier: Operating System :: OS Independent
Classifier: Topic :: Software Development
Requires-Dist: puput
Requires-Dist: lxml (==3.4.4)
Requires-Dist: requests (==2.22.0)
